setup.py
flockdoc/__init__.py
flockdoc/processor.py
flockdoc/renderer.py
flockdoc.egg-info/PKG-INFO
flockdoc.egg-info/SOURCES.txt
flockdoc.egg-info/dependency_links.txt
flockdoc.egg-info/requires.txt
flockdoc.egg-info/top_level.txt
flockdoc.egg-info/zip-safe
flockdoc/bin/flockdoc
flockdoc/content/__init__.py
flockdoc/content/code.py
flockdoc/content/markdown.py
flockdoc/content/static.py
flockdoc/templates/base.html
flockdoc/templates/layouts/code.html
flockdoc/templates/layouts/default.html