Metadata-Version: 1.0
Name: flockdoc
Version: 0.0.4
Summary: Create example API documentation in multiple languages
Home-page: https://github.com/brianhicks/flockdoc
Author: Brian Hicks
Author-email: brian@brianthicks.com
License: Apache
Platform: UNKNOWN
Classifier: Development Status :: 4 - Beta
Classifier: Intended Audience :: Developers
Classifier: License :: OSI Approved :: Apache Software License
